galaxy_importer/__init__.py
galaxy_importer/collection.py
galaxy_importer/config.py
galaxy_importer/constants.py
galaxy_importer/exceptions.py
galaxy_importer/finder.py
galaxy_importer/main.py
galaxy_importer/schema.py
galaxy_importer/ansible_test/__init__.py
galaxy_importer/ansible_test/job_template.yaml
galaxy_importer/ansible_test/builders/__init__.py
galaxy_importer/ansible_test/builders/local_image_build.py
galaxy_importer/ansible_test/container/Dockerfile
galaxy_importer/ansible_test/container/entrypoint.sh
galaxy_importer/ansible_test/runners/__init__.py
galaxy_importer/ansible_test/runners/base.py
galaxy_importer/ansible_test/runners/local_ansible_test.py
galaxy_importer/ansible_test/runners/local_image.py
galaxy_importer/ansible_test/runners/openshift_job.py
galaxy_importer/loaders/__init__.py
galaxy_importer/loaders/collection.py
galaxy_importer/loaders/content.py
galaxy_importer/loaders/doc_string.py
galaxy_importer/loaders/runtime_file.py
galaxy_importer/utils/__init__.py
galaxy_importer/utils/chksums.py
galaxy_importer/utils/markup.py
galaxy_importer/utils/requires_ansible_version.py
galaxy_importer/utils/spdx_licenses.json
galaxy_importer/utils/spdx_licenses.py
galaxy_importer/utils/string_utils.py
galaxy_importer-0.5.0.dist-info/LICENSE
galaxy_importer-0.5.0.dist-info/METADATA
galaxy_importer-0.5.0.dist-info/WHEEL
galaxy_importer-0.5.0.dist-info/top_level.txt
galaxy_importer-0.5.0.dist-info/RECORD
