Metadata-Version: 2.1
Name: galaxy-importer
Version: 0.5.0
Summary: Galaxy content importer
Home-page: https://github.com/ansible/galaxy-importer
Author: Red Hat, Inc.
Author-email: info@ansible.com
License: Apache-2.0
Classifier: License :: OSI Approved :: Apache Software License
Classifier: Operating System :: OS Independent
Classifier: Programming Language :: Python :: 3
License-File: LICENSE
Requires-Dist: ansible-core
Requires-Dist: ansible-builder (<2.0,>=1.0.1)
Requires-Dist: ansible-lint (<=6.14.3,>=6.2.2)
Requires-Dist: attrs (<23,>=21.4.0)
Requires-Dist: bleach (<4,>=3.3.0)
Requires-Dist: bleach-allowlist (<2,>=1.0.3)
Requires-Dist: flake8 (<7,>=5.0.0)
Requires-Dist: markdown (<4,>=3.3.4)
Requires-Dist: pyyaml (<7,>=5.4.1)
Requires-Dist: requests (<3,>=2.28.0)
Requires-Dist: semantic-version (<3,>=2.9.0)
Provides-Extra: dev
Requires-Dist: black (>=21.7b0) ; extra == 'dev'
Requires-Dist: GitPython (>=3.1.20) ; extra == 'dev'
Requires-Dist: pyfakefs (<5,>=4.4.0) ; extra == 'dev'
Requires-Dist: pytest (<8,>=7.0.0) ; extra == 'dev'
Requires-Dist: pytest-cov (<5,>=3.0.0) ; extra == 'dev'
Requires-Dist: pytest-mock (<4,>=3.8.0) ; extra == 'dev'
Requires-Dist: towncrier ; extra == 'dev'
